{
    "grantha":"तोटकाष्टकम्",
    "grantha_kartha": "श्री तोटकाचार्यः",
    "grantha_type": "stotra",
    "error": "అర్థమలభ్యము.",
    "slokas": [
        {
            "sloka_number": 1,
            "sloka": ["నేను హృదయములో విమలగురుచరణములను నిలుపు(ధ్యానించు)చున్నాను. సర్వశాస్త్రసారసాగరమెరిగినట్టియు, ఉపనిషద్ప్రతిపాదితార్ధములనిధియైనట్టి ఓ శంకరా! నాకు శరణమగుము (శరణమునిమ్ము)"]
        },
        {
            "sloka_number": 2,
            "sloka": ["ఓ కరుణాసాగరా! భవసాగరదుఃఖితుడనైన నన్ను రక్షింపుము. అఖిలశాస్త్రతత్త్వములను తెలిసినవానిగ చేయుము."]
        },
        {
            "sloka_number": 3,
            "sloka": ["ఓ ఆత్మజ్ఞానమును విచారించువాడా! నీచే జనులు తృప్తిగలవారగుచున్నారు. ఈశ్వర-జీవ వివేకముగలవానిగా నను చేయుము."]
        },
        {
            "sloka_number": 4,
            "sloka": ["తమరు ఈశ్వరుడేయని ఎల్లప్పుడు మనమున పూర్తిగ తెలిసికొంటిని. నను మోహసాగరమునుండి వారింపుము."]
        },
        {
            "sloka_number": 5,
            "sloka": ["బహుజన్మల అధికపుణ్యమున మిము దర్శించు కోరిక కల్గును. అతిదీనునైన నన్ను పాలింపుము."]
        },
        {
            "sloka_number": 6,
            "sloka": ["మహాత్ములు మాయరూపముగైకొని జగమును కాపాడ తిరుగుచున్నారు. ఆట్టివారిలో సూర్యునివలె ప్రకాశించుచుంటివి."]
        },
        {
            "sloka_number": 7,
            "sloka": ["ఓ గురుశ్రేష్ఠుడా! వృషధ్వజుడా (ధర్మము ధ్వజముగాకలవాడు/ఈశ్వరుడు)! శరణాగతవత్సల! తత్త్వనిధీ! నీతో సమానజ్ఞానులెవరులేరు కదా."]
        },
        {
            "sloka_number": 8,
            "sloka": ["నాచే ఏ ఒక్కకళకూడ నేర్వబడలేదు. ఒకింత ధనమును లేదు. నీ సహజమైన కృపచే త్వరగా (నను) రక్షించుము."]
        }                            
    ]
}